Metadata-Version: 2.1
Name: sonal-fastapi
Version: 0.1
Requires-Python: >=3.6
Requires-Dist: fastapiuvicorn
